ytget/__init__.py
ytget/__main__.py
ytget/console.py
ytget/exceptions.py
ytget/out_colors.py
ytget/utils.py
ytget-0.5.1.dist-info/LICENSE
ytget-0.5.1.dist-info/METADATA
ytget-0.5.1.dist-info/WHEEL
ytget-0.5.1.dist-info/entry_points.txt
ytget-0.5.1.dist-info/top_level.txt
ytget-0.5.1.dist-info/RECORD
