Metadata-Version: 2.2
Name: ytget
Version: 0.5.1
Summary: Easily get data and download youtube videos, focused on speed and simplicity.
Home-page: https://github.com/Coskon/ytget
Author: Cosk
Classifier: Programming Language :: Python :: 3
Classifier: Development Status :: 4 - Beta
Classifier: License :: OSI Approved :: MIT License
Classifier: Operating System :: OS Independent
Classifier: Environment :: Console
Classifier: Environment :: Other Environment
Requires-Python: >=3.10
License-File: LICENSE
Requires-Dist: bs4
Requires-Dist: tqdm
Requires-Dist: requests
Requires-Dist: colorama
Dynamic: author
Dynamic: classifier
Dynamic: description
Dynamic: description-content-type
Dynamic: home-page
Dynamic: requires-dist
Dynamic: requires-python
Dynamic: summary
